{
  "algorithm": "EliteLSGA",
  "instance": "WIP-FMS_05",
  "seed": 4,
  "parameters": {
    "pop_size": 100,
    "generations": 50
  },
  "result": {
    "makespan": 162,
    "runtime": 74.58071613311768,
    "blocking": 50
  },
  "history": {
    "best_fitness_per_generation": [
      222.0,
      203.0,
      183.0,
      183.0,
      183.0,
      183.0,
      183.0,
      183.0,
      181.0,
      181.0,
      181.0,
      181.0,
      181.0,
      181.0,
      181.0,
      181.0,
      181.0,
      179.0,
      175.0,
      166.0,
      166.0,
      166.0,
      166.0,
      166.0,
      166.0,
      166.0,
      166.0,
      166.0,
      166.0,
      166.0,
      166.0,
      166.0,
      166.0,
      166.0,
      166.0,
      166.0,
      166.0,
      166.0,
      166.0,
      166.0,
      166.0,
      166.0,
      166.0,
      166.0,
      162.0,
      162.0,
      162.0,
      162.0,
      162.0,
      162.0,
      162.0
    ]
  }
}