{
  "algorithm": "EliteLSGA",
  "instance": "WIP-FMS_08",
  "seed": 8,
  "parameters": {
    "pop_size": 100,
    "generations": 50
  },
  "result": {
    "makespan": 200,
    "runtime": 76.14672112464905,
    "blocking": 16
  },
  "history": {
    "best_fitness_per_generation": [
      234.0,
      222.0,
      214.0,
      210.0,
      210.0,
      210.0,
      210.0,
      210.0,
      210.0,
      210.0,
      210.0,
      210.0,
      210.0,
      210.0,
      210.0,
      210.0,
      202.0,
      202.0,
      202.0,
      202.0,
      202.0,
      202.0,
      200.0,
      200.0,
      200.0,
      200.0,
      200.0,
      200.0,
      200.0,
      200.0,
      200.0,
      200.0,
      200.0,
      200.0,
      200.0,
      200.0,
      200.0,
      200.0,
      200.0,
      200.0,
      200.0,
      200.0,
      200.0,
      200.0,
      200.0,
      200.0,
      200.0,
      200.0,
      200.0,
      200.0,
      200.0
    ]
  }
}