{
  "algorithm": "EliteLSGA",
  "instance": "WIP-FMS_11",
  "seed": 8,
  "parameters": {
    "pop_size": 100,
    "generations": 50
  },
  "result": {
    "makespan": 300,
    "runtime": 490.8646719455719,
    "blocking": 184
  },
  "history": {
    "best_fitness_per_generation": [
      344.0,
      342.0,
      339.0,
      332.0,
      332.0,
      332.0,
      326.0,
      326.0,
      318.0,
      318.0,
      314.0,
      313.0,
      313.0,
      313.0,
      313.0,
      313.0,
      313.0,
      313.0,
      313.0,
      312.0,
      307.0,
      305.0,
      305.0,
      305.0,
      305.0,
      305.0,
      305.0,
      305.0,
      305.0,
      305.0,
      305.0,
      305.0,
      305.0,
      305.0,
      305.0,
      305.0,
      305.0,
      305.0,
      305.0,
      305.0,
      305.0,
      305.0,
      305.0,
      305.0,
      305.0,
      305.0,
      305.0,
      305.0,
      305.0,
      300.0,
      300.0
    ]
  }
}