{
  "algorithm": "EliteLSGA",
  "instance": "WIP-FMS_16",
  "seed": 9,
  "parameters": {
    "pop_size": 100,
    "generations": 50
  },
  "result": {
    "makespan": 438,
    "runtime": 613.4372408390045,
    "blocking": 0
  },
  "history": {
    "best_fitness_per_generation": [
      507.0,
      468.0,
      457.0,
      457.0,
      457.0,
      457.0,
      457.0,
      457.0,
      457.0,
      457.0,
      457.0,
      457.0,
      453.0,
      453.0,
      453.0,
      453.0,
      453.0,
      450.0,
      450.0,
      450.0,
      450.0,
      446.0,
      446.0,
      446.0,
      446.0,
      443.0,
      443.0,
      443.0,
      443.0,
      443.0,
      443.0,
      443.0,
      443.0,
      443.0,
      443.0,
      443.0,
      443.0,
      443.0,
      443.0,
      443.0,
      443.0,
      443.0,
      443.0,
      443.0,
      443.0,
      443.0,
      443.0,
      438.0,
      438.0,
      438.0,
      438.0
    ]
  }
}