{
  "algorithm": "EliteLSGA",
  "instance": "WIP-FMS_03",
  "seed": 7,
  "parameters": {
    "pop_size": 100,
    "generations": 50
  },
  "result": {
    "makespan": 99,
    "runtime": 6.076343059539795,
    "blocking": 0
  },
  "history": {
    "best_fitness_per_generation": [
      104.0,
      101.0,
      101.0,
      101.0,
      101.0,
      101.0,
      101.0,
      101.0,
      101.0,
      101.0,
      101.0,
      101.0,
      101.0,
      101.0,
      101.0,
      101.0,
      100.0,
      100.0,
      99.0,
      99.0,
      99.0,
      99.0,
      99.0,
      99.0,
      99.0,
      99.0,
      99.0,
      99.0,
      99.0,
      99.0,
      99.0,
      99.0,
      99.0,
      99.0,
      99.0,
      99.0,
      99.0,
      99.0,
      99.0,
      99.0,
      99.0,
      99.0,
      99.0,
      99.0,
      99.0,
      99.0,
      99.0,
      99.0,
      99.0,
      99.0,
      99.0
    ]
  }
}