{
  "run_timestamp": "2026-04-13T06:59:36",
  "instance_name": "WIP-FMS_07",
  "instance_path": "data/instances/WIP-FMS/WIP-FMS_07.json",
  "trial_id": 14,
  "seed": 2,
  "factor_levels": {
    "PS": 300,
    "Pc": 0.8,
    "Pm": 0.3,
    "LS": 4
  },
  "algorithm": "EMTGLocalGAV2",
  "algorithm_parameters": {
    "pop_size": 100,
    "global_pop_size": 100,
    "local_pop_size": 100,
    "max_evaluations": 100000,
    "snapshot_interval": null,
    "crossover_rate": 0.8,
    "os_mutation_rate": 0.3,
    "ms_mutation_rate": 0.3,
    "tournament_size": 2,
    "gat_improve_window": 5,
    "gat_improve_threshold": 0.005,
    "local_elite_count": 4,
    "local_neighbors_per_elite": 6,
    "local_os_mutation_rate": 0.4,
    "local_ms_mutation_rate": 0.4,
    "seed": 2
  },
  "representative_result": {
    "makespan": 209,
    "shortage": 299.0,
    "runtime": 1611.629457950592,
    "n_evaluations": 100000
  },
  "pareto_front": [
    {
      "makespan": 213,
      "shortage": 257.0,
      "OS": [
        "J51",
        "J56",
        "J42",
        "J28",
        "J5",
        "J44",
        "J32",
        "J52",
        "J53",
        "J8",
        "J37",
        "J57",
        "J41",
        "J47",
        "J40",
        "J20",
        "J50",
        "J45",
        "J20",
        "J23",
        "J39",
        "J55",
        "J44",
        "J35",
        "J28",
        "J58",
        "J11",
        "J37",
        "J25",
        "J26",
        "J50",
        "J33",
        "J38",
        "J28",
        "J14",
        "J4",
        "J2",
        "J27",
        "J9",
        "J46",
        "J42",
        "J32",
        "J57",
        "J39",
        "J32",
        "J14",
        "J31",
        "J53",
        "J35",
        "J12",
        "J49",
        "J24",
        "J8",
        "J17",
        "J48",
        "J45",
        "J10",
        "J13",
        "J40",
        "J3",
        "J4",
        "J21",
        "J36",
        "J17",
        "J30",
        "J53",
        "J36",
        "J31",
        "J56",
        "J42",
        "J38",
        "J19",
        "J15",
        "J47",
        "J48",
        "J26",
        "J19",
        "J23",
        "J22",
        "J16",
        "J28",
        "J34",
        "J40",
        "J34",
        "J44",
        "J7",
        "J34",
        "J13",
        "J30",
        "J18",
        "J25",
        "J57",
        "J57",
        "J58",
        "J42",
        "J41",
        "J2",
        "J49",
        "J8",
        "J53",
        "J51",
        "J24",
        "J51",
        "J16",
        "J24",
        "J59",
        "J22",
        "J4",
        "J46",
        "J52",
        "J46",
        "J20",
        "J2",
        "J15",
        "J18",
        "J60",
        "J9",
        "J16",
        "J13",
        "J45",
        "J7",
        "J1",
        "J41",
        "J26",
        "J32",
        "J10",
        "J43",
        "J44",
        "J52",
        "J25",
        "J37",
        "J49",
        "J51",
        "J19",
        "J7",
        "J48",
        "J54",
        "J59",
        "J23",
        "J43",
        "J43",
        "J16",
        "J45",
        "J12",
        "J33",
        "J20",
        "J3",
        "J11",
        "J25",
        "J51",
        "J52",
        "J18",
        "J30",
        "J20",
        "J6",
        "J31",
        "J38",
        "J6",
        "J12",
        "J32",
        "J1",
        "J37",
        "J43",
        "J29",
        "J27",
        "J1",
        "J47",
        "J42",
        "J16",
        "J57",
        "J22",
        "J34",
        "J55",
        "J43",
        "J53",
        "J17",
        "J6",
        "J40",
        "J18",
        "J6",
        "J19",
        "J31",
        "J23",
        "J60",
        "J49",
        "J1",
        "J45",
        "J7",
        "J50",
        "J54",
        "J55",
        "J10",
        "J38",
        "J56",
        "J7",
        "J28",
        "J14",
        "J2",
        "J11",
        "J55",
        "J2",
        "J58",
        "J48",
        "J15",
        "J27",
        "J47",
        "J4",
        "J55",
        "J50",
        "J36",
        "J44",
        "J21",
        "J33",
        "J5",
        "J11",
        "J5",
        "J26",
        "J29",
        "J21",
        "J14",
        "J8",
        "J5",
        "J34",
        "J21",
        "J15",
        "J49",
        "J22",
        "J9",
        "J13",
        "J12",
        "J39",
        "J56",
        "J60",
        "J33",
        "J3",
        "J54",
        "J17",
        "J46",
        "J31",
        "J24",
        "J25",
        "J23",
        "J24",
        "J58",
        "J13",
        "J35",
        "J56",
        "J19",
        "J46",
        "J10",
        "J35",
        "J29",
        "J60",
        "J30",
        "J58",
        "J29",
        "J6",
        "J50",
        "J41",
        "J9",
        "J5",
        "J26",
        "J14",
        "J30",
        "J27",
        "J59",
        "J48",
        "J52",
        "J29",
        "J36",
        "J54",
        "J21",
        "J39",
        "J35",
        "J60",
        "J47",
        "J39",
        "J17",
        "J9",
        "J40",
        "J12",
        "J59",
        "J11",
        "J37",
        "J18",
        "J38",
        "J3",
        "J15",
        "J36",
        "J41",
        "J3",
        "J1",
        "J10",
        "J59",
        "J27",
        "J8",
        "J33",
        "J22",
        "J4",
        "J54"
      ],
      "MS": [
        "M0b",
        "M1a",
        "M2b",
        "M3a",
        "M4a",
        "M0a",
        "M1a",
        "M2b",
        "M3c",
        "M4a",
        "M0a",
        "M1c",
        "M2a",
        "M3a",
        "M4c",
        "M0a",
        "M1a",
        "M2a",
        "M3c",
        "M4b",
        "M0a",
        "M1c",
        "M2a",
        "M3a",
        "M4a",
        "M0a",
        "M1a",
        "M2a",
        "M3b",
        "M4a",
        "M0a",
        "M1b",
        "M2b",
        "M3a",
        "M4a",
        "M0b",
        "M1a",
        "M2a",
        "M3b",
        "M4a",
        "M0c",
        "M1a",
        "M2a",
        "M3b",
        "M4a",
        "M0c",
        "M1b",
        "M2c",
        "M3a",
        "M4a",
        "M0a",
        "M1c",
        "M2c",
        "M3c",
        "M4a",
        "M0a",
        "M1a",
        "M2a",
        "M3b",
        "M4c",
        "M0a",
        "M1a",
        "M2a",
        "M3b",
        "M4a",
        "M0a",
        "M1c",
        "M2a",
        "M3a",
        "M4a",
        "M0a",
        "M1a",
        "M2c",
        "M3b",
        "M4a",
        "M0b",
        "M1a",
        "M2c",
        "M3b",
        "M4b",
        "M0a",
        "M1a",
        "M2a",
        "M3b",
        "M4a",
        "M0a",
        "M1a",
        "M2a",
        "M3a",
        "M4a",
        "M0a",
        "M1a",
        "M2a",
        "M3a",
        "M4a",
        "M0a",
        "M1a",
        "M2b",
        "M3a",
        "M4a",
        "M0a",
        "M1c",
        "M2c",
        "M3b",
        "M4b",
        "M0a",
        "M1a",
        "M2b",
        "M3a",
        "M4a",
        "M0a",
        "M1a",
        "M2a",
        "M3a",
        "M4a",
        "M0a",
        "M1a",
        "M2b",
        "M3a",
        "M4a",
        "M0a",
        "M1a",
        "M2a",
        "M3a",
        "M4a",
        "M0a",
        "M1a",
        "M2a",
        "M3a",
        "M4c",
        "M0a",
        "M1a",
        "M2b",
        "M3a",
        "M4a",
        "M0a",
        "M1b",
        "M2a",
        "M3a",
        "M4a",
        "M0c",
        "M1a",
        "M2a",
        "M3a",
        "M4a",
        "M0a",
        "M1b",
        "M2c",
        "M3a",
        "M4c",
        "M0a",
        "M1b",
        "M2a",
        "M3a",
        "M4c",
        "M0c",
        "M1a",
        "M2b",
        "M3a",
        "M4b",
        "M0a",
        "M1c",
        "M2a",
        "M3a",
        "M4a",
        "M0c",
        "M1a",
        "M2a",
        "M3a",
        "M4c",
        "M0a",
        "M1a",
        "M2b",
        "M3a",
        "M4c",
        "M0a",
        "M1a",
        "M2b",
        "M3a",
        "M4c",
        "M0b",
        "M1a",
        "M2a",
        "M3b",
        "M4a",
        "M0a",
        "M1c",
        "M2a",
        "M3a",
        "M4a",
        "M0b",
        "M1c",
        "M2a",
        "M3a",
        "M4a",
        "M0a",
        "M1b",
        "M2a",
        "M3b",
        "M4a",
        "M0a",
        "M1a",
        "M2c",
        "M3a",
        "M4c",
        "M0a",
        "M1b",
        "M2a",
        "M3c",
        "M4c",
        "M0a",
        "M1a",
        "M2a",
        "M3b",
        "M4a",
        "M0a",
        "M1a",
        "M2b",
        "M3c",
        "M4a",
        "M0a",
        "M1a",
        "M2a",
        "M3a",
        "M4a",
        "M0a",
        "M1c",
        "M2b",
        "M3a",
        "M4a",
        "M0c",
        "M1a",
        "M2a",
        "M3a",
        "M4c",
        "M0c",
        "M1b",
        "M2c",
        "M3b",
        "M4a",
        "M0a",
        "M1c",
        "M2a",
        "M3c",
        "M4a",
        "M0c",
        "M1a",
        "M2a",
        "M3b",
        "M4a",
        "M0a",
        "M1a",
        "M2a",
        "M3b",
        "M4a",
        "M0b",
        "M1c",
        "M2a",
        "M3a",
        "M4b",
        "M0b",
        "M1c",
        "M2a",
        "M3a",
        "M4a",
        "M0a",
        "M1a",
        "M2b",
        "M3b",
        "M4c",
        "M0a",
        "M1a",
        "M2c",
        "M3a",
        "M4a",
        "M0c",
        "M1a",
        "M2a",
        "M3a",
        "M4c",
        "M0a",
        "M1c",
        "M2a",
        "M3a",
        "M4b",
        "M0b",
        "M1c",
        "M2b",
        "M3b",
        "M4c",
        "M0a",
        "M1a",
        "M2a",
        "M3b",
        "M4a",
        "M0a",
        "M1a",
        "M2a",
        "M3a",
        "M4a"
      ]
    },
    {
      "makespan": 212,
      "shortage": 258.0,
      "OS": [
        "J51",
        "J56",
        "J42",
        "J28",
        "J5",
        "J44",
        "J32",
        "J52",
        "J53",
        "J8",
        "J37",
        "J57",
        "J41",
        "J47",
        "J40",
        "J20",
        "J50",
        "J45",
        "J20",
        "J23",
        "J39",
        "J55",
        "J44",
        "J35",
        "J28",
        "J58",
        "J11",
        "J37",
        "J25",
        "J26",
        "J50",
        "J33",
        "J38",
        "J28",
        "J14",
        "J4",
        "J2",
        "J27",
        "J9",
        "J46",
        "J42",
        "J32",
        "J57",
        "J39",
        "J32",
        "J14",
        "J31",
        "J53",
        "J35",
        "J12",
        "J49",
        "J24",
        "J8",
        "J17",
        "J48",
        "J45",
        "J10",
        "J13",
        "J40",
        "J3",
        "J4",
        "J21",
        "J36",
        "J17",
        "J30",
        "J53",
        "J36",
        "J31",
        "J56",
        "J42",
        "J38",
        "J19",
        "J15",
        "J47",
        "J48",
        "J26",
        "J19",
        "J23",
        "J22",
        "J16",
        "J28",
        "J34",
        "J40",
        "J34",
        "J44",
        "J7",
        "J34",
        "J13",
        "J30",
        "J18",
        "J25",
        "J57",
        "J57",
        "J58",
        "J42",
        "J41",
        "J2",
        "J49",
        "J8",
        "J53",
        "J51",
        "J24",
        "J51",
        "J16",
        "J24",
        "J59",
        "J22",
        "J4",
        "J46",
        "J52",
        "J46",
        "J20",
        "J2",
        "J15",
        "J18",
        "J60",
        "J9",
        "J16",
        "J13",
        "J45",
        "J7",
        "J1",
        "J41",
        "J26",
        "J32",
        "J10",
        "J43",
        "J44",
        "J51",
        "J52",
        "J25",
        "J37",
        "J49",
        "J19",
        "J7",
        "J48",
        "J54",
        "J59",
        "J23",
        "J43",
        "J43",
        "J16",
        "J45",
        "J12",
        "J33",
        "J20",
        "J3",
        "J11",
        "J25",
        "J51",
        "J52",
        "J18",
        "J30",
        "J20",
        "J6",
        "J31",
        "J38",
        "J6",
        "J12",
        "J32",
        "J1",
        "J37",
        "J43",
        "J29",
        "J27",
        "J1",
        "J47",
        "J42",
        "J16",
        "J57",
        "J22",
        "J34",
        "J55",
        "J43",
        "J53",
        "J17",
        "J6",
        "J40",
        "J18",
        "J6",
        "J19",
        "J31",
        "J23",
        "J60",
        "J49",
        "J1",
        "J45",
        "J7",
        "J50",
        "J54",
        "J55",
        "J10",
        "J38",
        "J56",
        "J7",
        "J28",
        "J14",
        "J2",
        "J11",
        "J55",
        "J2",
        "J58",
        "J48",
        "J15",
        "J27",
        "J47",
        "J4",
        "J55",
        "J50",
        "J36",
        "J44",
        "J21",
        "J33",
        "J5",
        "J11",
        "J5",
        "J26",
        "J29",
        "J21",
        "J14",
        "J8",
        "J5",
        "J34",
        "J21",
        "J15",
        "J49",
        "J22",
        "J9",
        "J13",
        "J12",
        "J39",
        "J56",
        "J60",
        "J33",
        "J3",
        "J54",
        "J17",
        "J46",
        "J31",
        "J24",
        "J25",
        "J23",
        "J24",
        "J58",
        "J13",
        "J35",
        "J56",
        "J19",
        "J46",
        "J10",
        "J35",
        "J29",
        "J60",
        "J30",
        "J58",
        "J29",
        "J6",
        "J50",
        "J41",
        "J9",
        "J5",
        "J26",
        "J14",
        "J30",
        "J27",
        "J59",
        "J48",
        "J52",
        "J29",
        "J36",
        "J54",
        "J21",
        "J39",
        "J35",
        "J60",
        "J47",
        "J39",
        "J17",
        "J9",
        "J40",
        "J12",
        "J59",
        "J11",
        "J37",
        "J18",
        "J38",
        "J3",
        "J15",
        "J36",
        "J41",
        "J3",
        "J1",
        "J10",
        "J59",
        "J27",
        "J8",
        "J33",
        "J22",
        "J4",
        "J54"
      ],
      "MS": [
        "M0b",
        "M1a",
        "M2b",
        "M3a",
        "M4a",
        "M0a",
        "M1a",
        "M2b",
        "M3c",
        "M4a",
        "M0a",
        "M1c",
        "M2a",
        "M3a",
        "M4c",
        "M0a",
        "M1a",
        "M2a",
        "M3c",
        "M4b",
        "M0a",
        "M1c",
        "M2a",
        "M3a",
        "M4a",
        "M0a",
        "M1a",
        "M2a",
        "M3b",
        "M4a",
        "M0a",
        "M1b",
        "M2b",
        "M3a",
        "M4a",
        "M0b",
        "M1a",
        "M2a",
        "M3b",
        "M4a",
        "M0c",
        "M1a",
        "M2a",
        "M3b",
        "M4a",
        "M0c",
        "M1b",
        "M2c",
        "M3a",
        "M4a",
        "M0a",
        "M1c",
        "M2c",
        "M3c",
        "M4a",
        "M0a",
        "M1a",
        "M2a",
        "M3b",
        "M4c",
        "M0a",
        "M1a",
        "M2a",
        "M3b",
        "M4a",
        "M0a",
        "M1c",
        "M2a",
        "M3a",
        "M4a",
        "M0a",
        "M1a",
        "M2c",
        "M3b",
        "M4a",
        "M0b",
        "M1a",
        "M2c",
        "M3b",
        "M4b",
        "M0a",
        "M1a",
        "M2a",
        "M3b",
        "M4a",
        "M0a",
        "M1a",
        "M2a",
        "M3a",
        "M4a",
        "M0a",
        "M1a",
        "M2a",
        "M3a",
        "M4a",
        "M0a",
        "M1a",
        "M2b",
        "M3a",
        "M4a",
        "M0a",
        "M1c",
        "M2c",
        "M3b",
        "M4b",
        "M0a",
        "M1a",
        "M2b",
        "M3a",
        "M4a",
        "M0a",
        "M1a",
        "M2a",
        "M3a",
        "M4a",
        "M0a",
        "M1a",
        "M2b",
        "M3a",
        "M4a",
        "M0a",
        "M1a",
        "M2a",
        "M3a",
        "M4a",
        "M0a",
        "M1a",
        "M2a",
        "M3a",
        "M4c",
        "M0a",
        "M1a",
        "M2b",
        "M3a",
        "M4a",
        "M0a",
        "M1b",
        "M2a",
        "M3a",
        "M4a",
        "M0c",
        "M1a",
        "M2a",
        "M3a",
        "M4a",
        "M0a",
        "M1b",
        "M2c",
        "M3a",
        "M4c",
        "M0a",
        "M1b",
        "M2a",
        "M3a",
        "M4c",
        "M0c",
        "M1a",
        "M2b",
        "M3a",
        "M4b",
        "M0a",
        "M1c",
        "M2a",
        "M3a",
        "M4a",
        "M0c",
        "M1a",
        "M2a",
        "M3a",
        "M4c",
        "M0a",
        "M1a",
        "M2b",
        "M3c",
        "M4c",
        "M0a",
        "M1a",
        "M2b",
        "M3a",
        "M4c",
        "M0b",
        "M1a",
        "M2a",
        "M3b",
        "M4a",
        "M0a",
        "M1c",
        "M2a",
        "M3a",
        "M4a",
        "M0b",
        "M1c",
        "M2a",
        "M3a",
        "M4a",
        "M0a",
        "M1b",
        "M2a",
        "M3b",
        "M4a",
        "M0a",
        "M1a",
        "M2c",
        "M3a",
        "M4c",
        "M0a",
        "M1b",
        "M2a",
        "M3c",
        "M4c",
        "M0a",
        "M1a",
        "M2a",
        "M3b",
        "M4a",
        "M0a",
        "M1a",
        "M2b",
        "M3c",
        "M4a",
        "M0a",
        "M1a",
        "M2a",
        "M3a",
        "M4a",
        "M0a",
        "M1c",
        "M2b",
        "M3a",
        "M4a",
        "M0c",
        "M1a",
        "M2a",
        "M3a",
        "M4c",
        "M0c",
        "M1b",
        "M2c",
        "M3b",
        "M4a",
        "M0a",
        "M1c",
        "M2a",
        "M3c",
        "M4a",
        "M0c",
        "M1a",
        "M2a",
        "M3b",
        "M4a",
        "M0a",
        "M1a",
        "M2a",
        "M3b",
        "M4a",
        "M0b",
        "M1c",
        "M2a",
        "M3a",
        "M4b",
        "M0b",
        "M1c",
        "M2a",
        "M3a",
        "M4a",
        "M0a",
        "M1a",
        "M2b",
        "M3b",
        "M4c",
        "M0a",
        "M1a",
        "M2c",
        "M3a",
        "M4a",
        "M0c",
        "M1a",
        "M2a",
        "M3a",
        "M4c",
        "M0a",
        "M1c",
        "M2a",
        "M3a",
        "M4b",
        "M0b",
        "M1c",
        "M2b",
        "M3b",
        "M4c",
        "M0a",
        "M1a",
        "M2a",
        "M3b",
        "M4a",
        "M0a",
        "M1a",
        "M2a",
        "M3a",
        "M4a"
      ]
    },
    {
      "makespan": 211,
      "shortage": 282.0,
      "OS": [
        "J51",
        "J56",
        "J42",
        "J28",
        "J5",
        "J44",
        "J32",
        "J52",
        "J53",
        "J8",
        "J37",
        "J57",
        "J41",
        "J47",
        "J40",
        "J20",
        "J50",
        "J45",
        "J20",
        "J23",
        "J39",
        "J55",
        "J44",
        "J35",
        "J28",
        "J58",
        "J11",
        "J37",
        "J25",
        "J26",
        "J50",
        "J33",
        "J38",
        "J28",
        "J14",
        "J4",
        "J2",
        "J27",
        "J9",
        "J46",
        "J42",
        "J32",
        "J57",
        "J39",
        "J32",
        "J14",
        "J31",
        "J53",
        "J35",
        "J12",
        "J49",
        "J24",
        "J8",
        "J17",
        "J48",
        "J45",
        "J10",
        "J13",
        "J40",
        "J3",
        "J4",
        "J21",
        "J36",
        "J17",
        "J30",
        "J53",
        "J36",
        "J31",
        "J56",
        "J42",
        "J38",
        "J19",
        "J15",
        "J47",
        "J48",
        "J26",
        "J19",
        "J23",
        "J22",
        "J16",
        "J28",
        "J34",
        "J40",
        "J34",
        "J44",
        "J7",
        "J34",
        "J13",
        "J30",
        "J18",
        "J25",
        "J57",
        "J57",
        "J58",
        "J42",
        "J41",
        "J2",
        "J49",
        "J8",
        "J53",
        "J51",
        "J24",
        "J51",
        "J16",
        "J24",
        "J59",
        "J22",
        "J4",
        "J46",
        "J52",
        "J46",
        "J20",
        "J2",
        "J15",
        "J18",
        "J60",
        "J9",
        "J16",
        "J13",
        "J45",
        "J7",
        "J1",
        "J41",
        "J26",
        "J32",
        "J10",
        "J43",
        "J44",
        "J52",
        "J25",
        "J37",
        "J49",
        "J51",
        "J19",
        "J7",
        "J48",
        "J54",
        "J59",
        "J23",
        "J43",
        "J43",
        "J16",
        "J45",
        "J12",
        "J33",
        "J20",
        "J3",
        "J11",
        "J25",
        "J51",
        "J52",
        "J18",
        "J30",
        "J20",
        "J6",
        "J31",
        "J38",
        "J6",
        "J12",
        "J32",
        "J1",
        "J37",
        "J43",
        "J29",
        "J27",
        "J1",
        "J47",
        "J42",
        "J16",
        "J57",
        "J22",
        "J34",
        "J55",
        "J43",
        "J53",
        "J17",
        "J6",
        "J40",
        "J18",
        "J6",
        "J19",
        "J31",
        "J23",
        "J60",
        "J49",
        "J1",
        "J45",
        "J7",
        "J50",
        "J54",
        "J55",
        "J10",
        "J38",
        "J56",
        "J7",
        "J28",
        "J14",
        "J2",
        "J11",
        "J55",
        "J2",
        "J58",
        "J48",
        "J15",
        "J27",
        "J47",
        "J4",
        "J55",
        "J50",
        "J36",
        "J44",
        "J21",
        "J33",
        "J5",
        "J11",
        "J5",
        "J26",
        "J29",
        "J21",
        "J14",
        "J8",
        "J5",
        "J34",
        "J21",
        "J15",
        "J49",
        "J22",
        "J9",
        "J13",
        "J12",
        "J39",
        "J56",
        "J60",
        "J33",
        "J3",
        "J54",
        "J17",
        "J46",
        "J31",
        "J24",
        "J25",
        "J23",
        "J24",
        "J58",
        "J13",
        "J35",
        "J56",
        "J19",
        "J46",
        "J10",
        "J35",
        "J29",
        "J60",
        "J30",
        "J58",
        "J29",
        "J6",
        "J50",
        "J41",
        "J9",
        "J5",
        "J26",
        "J14",
        "J30",
        "J27",
        "J59",
        "J48",
        "J52",
        "J29",
        "J36",
        "J54",
        "J21",
        "J39",
        "J35",
        "J60",
        "J47",
        "J39",
        "J17",
        "J9",
        "J40",
        "J12",
        "J59",
        "J11",
        "J37",
        "J18",
        "J38",
        "J3",
        "J15",
        "J36",
        "J41",
        "J3",
        "J1",
        "J10",
        "J59",
        "J27",
        "J8",
        "J33",
        "J22",
        "J4",
        "J54"
      ],
      "MS": [
        "M0b",
        "M1a",
        "M2b",
        "M3a",
        "M4a",
        "M0a",
        "M1a",
        "M2b",
        "M3c",
        "M4a",
        "M0a",
        "M1c",
        "M2a",
        "M3a",
        "M4c",
        "M0a",
        "M1a",
        "M2a",
        "M3c",
        "M4b",
        "M0a",
        "M1c",
        "M2a",
        "M3a",
        "M4a",
        "M0a",
        "M1a",
        "M2a",
        "M3b",
        "M4a",
        "M0a",
        "M1b",
        "M2b",
        "M3a",
        "M4a",
        "M0b",
        "M1a",
        "M2a",
        "M3b",
        "M4a",
        "M0c",
        "M1a",
        "M2a",
        "M3b",
        "M4a",
        "M0c",
        "M1b",
        "M2c",
        "M3a",
        "M4a",
        "M0a",
        "M1c",
        "M2c",
        "M3c",
        "M4a",
        "M0a",
        "M1a",
        "M2a",
        "M3b",
        "M4c",
        "M0a",
        "M1a",
        "M2a",
        "M3b",
        "M4a",
        "M0a",
        "M1c",
        "M2a",
        "M3a",
        "M4a",
        "M0a",
        "M1a",
        "M2c",
        "M3b",
        "M4a",
        "M0b",
        "M1a",
        "M2c",
        "M3b",
        "M4b",
        "M0a",
        "M1a",
        "M2a",
        "M3b",
        "M4a",
        "M0a",
        "M1a",
        "M2a",
        "M3a",
        "M4a",
        "M0a",
        "M1a",
        "M2a",
        "M3a",
        "M4a",
        "M0a",
        "M1a",
        "M2b",
        "M3a",
        "M4a",
        "M0a",
        "M1c",
        "M2c",
        "M3b",
        "M4b",
        "M0a",
        "M1a",
        "M2b",
        "M3a",
        "M4a",
        "M0a",
        "M1a",
        "M2a",
        "M3a",
        "M4a",
        "M0a",
        "M1a",
        "M2b",
        "M3a",
        "M4a",
        "M0a",
        "M1a",
        "M2a",
        "M3a",
        "M4a",
        "M0a",
        "M1a",
        "M2a",
        "M3a",
        "M4c",
        "M0a",
        "M1a",
        "M2b",
        "M3a",
        "M4a",
        "M0a",
        "M1b",
        "M2a",
        "M3a",
        "M4a",
        "M0c",
        "M1a",
        "M2a",
        "M3a",
        "M4a",
        "M0a",
        "M1b",
        "M2c",
        "M3a",
        "M4c",
        "M0a",
        "M1b",
        "M2a",
        "M3a",
        "M4c",
        "M0c",
        "M1a",
        "M2b",
        "M3a",
        "M4b",
        "M0a",
        "M1c",
        "M2a",
        "M3a",
        "M4a",
        "M0c",
        "M1a",
        "M2a",
        "M3a",
        "M4c",
        "M0a",
        "M1a",
        "M2b",
        "M3a",
        "M4c",
        "M0a",
        "M1a",
        "M2b",
        "M3a",
        "M4c",
        "M0b",
        "M1a",
        "M2a",
        "M3b",
        "M4a",
        "M0a",
        "M1c",
        "M2a",
        "M3a",
        "M4a",
        "M0b",
        "M1c",
        "M2a",
        "M3b",
        "M4a",
        "M0a",
        "M1b",
        "M2a",
        "M3b",
        "M4a",
        "M0a",
        "M1a",
        "M2c",
        "M3a",
        "M4c",
        "M0a",
        "M1b",
        "M2a",
        "M3c",
        "M4c",
        "M0a",
        "M1a",
        "M2a",
        "M3b",
        "M4a",
        "M0a",
        "M1a",
        "M2b",
        "M3c",
        "M4a",
        "M0a",
        "M1a",
        "M2a",
        "M3a",
        "M4a",
        "M0a",
        "M1c",
        "M2b",
        "M3a",
        "M4a",
        "M0c",
        "M1a",
        "M2a",
        "M3a",
        "M4c",
        "M0c",
        "M1b",
        "M2c",
        "M3b",
        "M4a",
        "M0a",
        "M1c",
        "M2a",
        "M3c",
        "M4a",
        "M0c",
        "M1a",
        "M2a",
        "M3b",
        "M4a",
        "M0a",
        "M1a",
        "M2a",
        "M3b",
        "M4a",
        "M0b",
        "M1c",
        "M2a",
        "M3a",
        "M4b",
        "M0b",
        "M1c",
        "M2a",
        "M3a",
        "M4a",
        "M0a",
        "M1a",
        "M2b",
        "M3b",
        "M4c",
        "M0a",
        "M1a",
        "M2c",
        "M3a",
        "M4a",
        "M0c",
        "M1a",
        "M2a",
        "M3a",
        "M4c",
        "M0a",
        "M1c",
        "M2a",
        "M3a",
        "M4b",
        "M0b",
        "M1c",
        "M2b",
        "M3b",
        "M4c",
        "M0a",
        "M1a",
        "M2a",
        "M3b",
        "M4a",
        "M0a",
        "M1a",
        "M2a",
        "M3a",
        "M4a"
      ]
    },
    {
      "makespan": 209,
      "shortage": 299.0,
      "OS": [
        "J5",
        "J40",
        "J51",
        "J28",
        "J44",
        "J10",
        "J52",
        "J53",
        "J8",
        "J8",
        "J8",
        "J8",
        "J27",
        "J37",
        "J26",
        "J57",
        "J41",
        "J45",
        "J29",
        "J32",
        "J23",
        "J5",
        "J39",
        "J55",
        "J19",
        "J44",
        "J28",
        "J11",
        "J37",
        "J25",
        "J36",
        "J38",
        "J28",
        "J42",
        "J2",
        "J24",
        "J48",
        "J9",
        "J40",
        "J46",
        "J57",
        "J39",
        "J31",
        "J58",
        "J53",
        "J12",
        "J47",
        "J27",
        "J49",
        "J17",
        "J29",
        "J47",
        "J45",
        "J35",
        "J24",
        "J10",
        "J13",
        "J26",
        "J3",
        "J21",
        "J17",
        "J53",
        "J31",
        "J16",
        "J29",
        "J38",
        "J6",
        "J15",
        "J23",
        "J22",
        "J28",
        "J32",
        "J35",
        "J34",
        "J6",
        "J36",
        "J34",
        "J8",
        "J44",
        "J34",
        "J13",
        "J14",
        "J18",
        "J25",
        "J57",
        "J57",
        "J41",
        "J30",
        "J56",
        "J14",
        "J20",
        "J2",
        "J16",
        "J49",
        "J53",
        "J27",
        "J42",
        "J27",
        "J56",
        "J19",
        "J40",
        "J51",
        "J51",
        "J59",
        "J50",
        "J32",
        "J22",
        "J33",
        "J40",
        "J46",
        "J42",
        "J52",
        "J20",
        "J46",
        "J10",
        "J2",
        "J7",
        "J15",
        "J10",
        "J4",
        "J18",
        "J60",
        "J20",
        "J48",
        "J9",
        "J13",
        "J14",
        "J6",
        "J45",
        "J1",
        "J10",
        "J41",
        "J19",
        "J33",
        "J33",
        "J43",
        "J44",
        "J52",
        "J25",
        "J37",
        "J36",
        "J30",
        "J49",
        "J16",
        "J51",
        "J48",
        "J54",
        "J36",
        "J59",
        "J19",
        "J58",
        "J4",
        "J23",
        "J47",
        "J43",
        "J43",
        "J58",
        "J45",
        "J33",
        "J24",
        "J24",
        "J14",
        "J58",
        "J30",
        "J19",
        "J12",
        "J3",
        "J11",
        "J25",
        "J51",
        "J52",
        "J18",
        "J31",
        "J38",
        "J12",
        "J37",
        "J43",
        "J29",
        "J4",
        "J36",
        "J35",
        "J57",
        "J50",
        "J35",
        "J22",
        "J34",
        "J55",
        "J43",
        "J5",
        "J5",
        "J53",
        "J17",
        "J18",
        "J31",
        "J47",
        "J23",
        "J60",
        "J26",
        "J1",
        "J1",
        "J1",
        "J49",
        "J45",
        "J54",
        "J55",
        "J38",
        "J20",
        "J16",
        "J28",
        "J2",
        "J11",
        "J7",
        "J48",
        "J55",
        "J40",
        "J42",
        "J32",
        "J33",
        "J58",
        "J4",
        "J20",
        "J16",
        "J15",
        "J55",
        "J44",
        "J4",
        "J21",
        "J11",
        "J21",
        "J34",
        "J21",
        "J26",
        "J15",
        "J49",
        "J5",
        "J27",
        "J22",
        "J47",
        "J7",
        "J56",
        "J9",
        "J13",
        "J12",
        "J29",
        "J50",
        "J2",
        "J39",
        "J60",
        "J7",
        "J3",
        "J54",
        "J17",
        "J6",
        "J6",
        "J46",
        "J31",
        "J25",
        "J48",
        "J23",
        "J13",
        "J46",
        "J60",
        "J41",
        "J35",
        "J9",
        "J59",
        "J52",
        "J14",
        "J54",
        "J21",
        "J39",
        "J30",
        "J60",
        "J39",
        "J17",
        "J9",
        "J12",
        "J59",
        "J11",
        "J37",
        "J18",
        "J30",
        "J38",
        "J32",
        "J24",
        "J56",
        "J3",
        "J7",
        "J42",
        "J15",
        "J41",
        "J50",
        "J56",
        "J3",
        "J50",
        "J59",
        "J22",
        "J26",
        "J54",
        "J1"
      ],
      "MS": [
        "M0c",
        "M1a",
        "M2c",
        "M3a",
        "M4a",
        "M0c",
        "M1c",
        "M2b",
        "M3b",
        "M4b",
        "M0b",
        "M1c",
        "M2b",
        "M3a",
        "M4a",
        "M0a",
        "M1a",
        "M2a",
        "M3a",
        "M4b",
        "M0b",
        "M1c",
        "M2a",
        "M3a",
        "M4c",
        "M0b",
        "M1a",
        "M2a",
        "M3a",
        "M4a",
        "M0b",
        "M1a",
        "M2b",
        "M3a",
        "M4a",
        "M0a",
        "M1a",
        "M2b",
        "M3b",
        "M4b",
        "M0b",
        "M1a",
        "M2a",
        "M3b",
        "M4b",
        "M0c",
        "M1b",
        "M2c",
        "M3a",
        "M4a",
        "M0b",
        "M1a",
        "M2c",
        "M3b",
        "M4a",
        "M0c",
        "M1a",
        "M2b",
        "M3c",
        "M4a",
        "M0a",
        "M1a",
        "M2a",
        "M3a",
        "M4a",
        "M0a",
        "M1a",
        "M2a",
        "M3a",
        "M4a",
        "M0a",
        "M1a",
        "M2b",
        "M3b",
        "M4a",
        "M0c",
        "M1c",
        "M2a",
        "M3a",
        "M4b",
        "M0a",
        "M1a",
        "M2a",
        "M3a",
        "M4a",
        "M0c",
        "M1a",
        "M2b",
        "M3b",
        "M4a",
        "M0a",
        "M1a",
        "M2a",
        "M3c",
        "M4a",
        "M0a",
        "M1b",
        "M2b",
        "M3b",
        "M4a",
        "M0a",
        "M1a",
        "M2c",
        "M3b",
        "M4b",
        "M0a",
        "M1a",
        "M2b",
        "M3a",
        "M4a",
        "M0a",
        "M1b",
        "M2a",
        "M3a",
        "M4a",
        "M0a",
        "M1a",
        "M2c",
        "M3a",
        "M4c",
        "M0b",
        "M1a",
        "M2a",
        "M3c",
        "M4a",
        "M0a",
        "M1b",
        "M2a",
        "M3c",
        "M4c",
        "M0a",
        "M1b",
        "M2a",
        "M3a",
        "M4a",
        "M0a",
        "M1a",
        "M2a",
        "M3b",
        "M4a",
        "M0c",
        "M1a",
        "M2a",
        "M3c",
        "M4b",
        "M0a",
        "M1b",
        "M2c",
        "M3a",
        "M4c",
        "M0a",
        "M1b",
        "M2a",
        "M3c",
        "M4c",
        "M0b",
        "M1b",
        "M2b",
        "M3a",
        "M4c",
        "M0a",
        "M1a",
        "M2a",
        "M3a",
        "M4a",
        "M0b",
        "M1b",
        "M2a",
        "M3a",
        "M4a",
        "M0a",
        "M1a",
        "M2a",
        "M3a",
        "M4a",
        "M0b",
        "M1a",
        "M2b",
        "M3c",
        "M4c",
        "M0b",
        "M1c",
        "M2a",
        "M3a",
        "M4a",
        "M0b",
        "M1c",
        "M2a",
        "M3b",
        "M4a",
        "M0c",
        "M1c",
        "M2a",
        "M3b",
        "M4b",
        "M0a",
        "M1b",
        "M2a",
        "M3b",
        "M4a",
        "M0a",
        "M1a",
        "M2c",
        "M3b",
        "M4c",
        "M0a",
        "M1a",
        "M2a",
        "M3a",
        "M4c",
        "M0a",
        "M1a",
        "M2a",
        "M3a",
        "M4a",
        "M0a",
        "M1b",
        "M2b",
        "M3c",
        "M4a",
        "M0a",
        "M1b",
        "M2a",
        "M3a",
        "M4b",
        "M0a",
        "M1a",
        "M2b",
        "M3b",
        "M4a",
        "M0c",
        "M1b",
        "M2a",
        "M3a",
        "M4c",
        "M0c",
        "M1b",
        "M2a",
        "M3b",
        "M4a",
        "M0a",
        "M1c",
        "M2a",
        "M3b",
        "M4a",
        "M0a",
        "M1c",
        "M2a",
        "M3b",
        "M4b",
        "M0a",
        "M1a",
        "M2a",
        "M3a",
        "M4a",
        "M0b",
        "M1b",
        "M2a",
        "M3a",
        "M4b",
        "M0b",
        "M1c",
        "M2c",
        "M3a",
        "M4a",
        "M0a",
        "M1b",
        "M2b",
        "M3b",
        "M4a",
        "M0a",
        "M1a",
        "M2c",
        "M3a",
        "M4a",
        "M0c",
        "M1a",
        "M2c",
        "M3b",
        "M4a",
        "M0a",
        "M1a",
        "M2a",
        "M3a",
        "M4a",
        "M0b",
        "M1c",
        "M2a",
        "M3c",
        "M4b",
        "M0c",
        "M1a",
        "M2c",
        "M3a",
        "M4b",
        "M0a",
        "M1a",
        "M2a",
        "M3a",
        "M4a"
      ]
    },
    {
      "makespan": 208,
      "shortage": 326.0,
      "OS": [
        "J5",
        "J40",
        "J51",
        "J28",
        "J44",
        "J10",
        "J52",
        "J53",
        "J8",
        "J27",
        "J37",
        "J5",
        "J26",
        "J57",
        "J8",
        "J41",
        "J45",
        "J29",
        "J32",
        "J23",
        "J39",
        "J55",
        "J19",
        "J44",
        "J28",
        "J11",
        "J37",
        "J25",
        "J36",
        "J38",
        "J28",
        "J42",
        "J2",
        "J24",
        "J48",
        "J9",
        "J40",
        "J46",
        "J8",
        "J57",
        "J39",
        "J31",
        "J58",
        "J53",
        "J12",
        "J47",
        "J27",
        "J49",
        "J17",
        "J29",
        "J47",
        "J45",
        "J35",
        "J24",
        "J10",
        "J13",
        "J26",
        "J3",
        "J21",
        "J17",
        "J53",
        "J31",
        "J8",
        "J16",
        "J29",
        "J38",
        "J6",
        "J15",
        "J23",
        "J22",
        "J28",
        "J32",
        "J35",
        "J34",
        "J6",
        "J36",
        "J34",
        "J8",
        "J44",
        "J34",
        "J13",
        "J14",
        "J18",
        "J25",
        "J57",
        "J57",
        "J41",
        "J30",
        "J56",
        "J14",
        "J20",
        "J2",
        "J16",
        "J49",
        "J53",
        "J27",
        "J42",
        "J27",
        "J56",
        "J19",
        "J40",
        "J51",
        "J51",
        "J59",
        "J50",
        "J32",
        "J22",
        "J33",
        "J40",
        "J46",
        "J42",
        "J52",
        "J20",
        "J46",
        "J10",
        "J2",
        "J7",
        "J15",
        "J10",
        "J4",
        "J18",
        "J60",
        "J20",
        "J48",
        "J9",
        "J13",
        "J14",
        "J6",
        "J45",
        "J10",
        "J1",
        "J41",
        "J19",
        "J33",
        "J33",
        "J43",
        "J44",
        "J52",
        "J25",
        "J37",
        "J36",
        "J30",
        "J49",
        "J16",
        "J51",
        "J48",
        "J54",
        "J36",
        "J59",
        "J19",
        "J58",
        "J4",
        "J23",
        "J47",
        "J43",
        "J43",
        "J58",
        "J45",
        "J33",
        "J24",
        "J24",
        "J14",
        "J58",
        "J30",
        "J19",
        "J12",
        "J3",
        "J11",
        "J25",
        "J51",
        "J52",
        "J18",
        "J31",
        "J38",
        "J12",
        "J1",
        "J37",
        "J43",
        "J29",
        "J4",
        "J36",
        "J35",
        "J1",
        "J57",
        "J50",
        "J35",
        "J22",
        "J34",
        "J55",
        "J43",
        "J53",
        "J5",
        "J17",
        "J18",
        "J31",
        "J47",
        "J23",
        "J60",
        "J26",
        "J49",
        "J1",
        "J45",
        "J54",
        "J55",
        "J38",
        "J20",
        "J16",
        "J28",
        "J2",
        "J11",
        "J7",
        "J48",
        "J5",
        "J55",
        "J40",
        "J2",
        "J42",
        "J32",
        "J33",
        "J58",
        "J4",
        "J20",
        "J16",
        "J15",
        "J55",
        "J44",
        "J4",
        "J21",
        "J11",
        "J21",
        "J34",
        "J21",
        "J26",
        "J15",
        "J49",
        "J5",
        "J27",
        "J22",
        "J47",
        "J7",
        "J56",
        "J9",
        "J13",
        "J12",
        "J29",
        "J50",
        "J39",
        "J60",
        "J7",
        "J3",
        "J54",
        "J17",
        "J6",
        "J6",
        "J46",
        "J31",
        "J25",
        "J48",
        "J23",
        "J13",
        "J46",
        "J60",
        "J41",
        "J35",
        "J9",
        "J59",
        "J52",
        "J14",
        "J54",
        "J21",
        "J39",
        "J30",
        "J60",
        "J39",
        "J17",
        "J9",
        "J12",
        "J59",
        "J11",
        "J37",
        "J18",
        "J30",
        "J38",
        "J32",
        "J24",
        "J56",
        "J3",
        "J7",
        "J42",
        "J15",
        "J41",
        "J50",
        "J56",
        "J3",
        "J50",
        "J1",
        "J59",
        "J22",
        "J26",
        "J54"
      ],
      "MS": [
        "M0c",
        "M1a",
        "M2c",
        "M3a",
        "M4a",
        "M0c",
        "M1c",
        "M2b",
        "M3b",
        "M4b",
        "M0b",
        "M1c",
        "M2b",
        "M3a",
        "M4a",
        "M0a",
        "M1a",
        "M2a",
        "M3a",
        "M4b",
        "M0b",
        "M1c",
        "M2a",
        "M3a",
        "M4c",
        "M0b",
        "M1a",
        "M2a",
        "M3a",
        "M4a",
        "M0b",
        "M1a",
        "M2b",
        "M3a",
        "M4a",
        "M0a",
        "M1a",
        "M2b",
        "M3b",
        "M4b",
        "M0b",
        "M1a",
        "M2a",
        "M3b",
        "M4b",
        "M0c",
        "M1b",
        "M2c",
        "M3a",
        "M4a",
        "M0b",
        "M1a",
        "M2c",
        "M3b",
        "M4a",
        "M0c",
        "M1a",
        "M2b",
        "M3c",
        "M4a",
        "M0a",
        "M1a",
        "M2a",
        "M3a",
        "M4a",
        "M0a",
        "M1a",
        "M2a",
        "M3a",
        "M4a",
        "M0a",
        "M1a",
        "M2b",
        "M3b",
        "M4a",
        "M0c",
        "M1c",
        "M2a",
        "M3a",
        "M4b",
        "M0a",
        "M1a",
        "M2a",
        "M3a",
        "M4a",
        "M0c",
        "M1a",
        "M2b",
        "M3a",
        "M4a",
        "M0a",
        "M1a",
        "M2a",
        "M3c",
        "M4a",
        "M0a",
        "M1b",
        "M2b",
        "M3b",
        "M4a",
        "M0a",
        "M1a",
        "M2c",
        "M3b",
        "M4b",
        "M0a",
        "M1a",
        "M2b",
        "M3a",
        "M4a",
        "M0a",
        "M1b",
        "M2a",
        "M3a",
        "M4a",
        "M0a",
        "M1a",
        "M2c",
        "M3a",
        "M4c",
        "M0b",
        "M1a",
        "M2a",
        "M3c",
        "M4a",
        "M0a",
        "M1b",
        "M2a",
        "M3c",
        "M4c",
        "M0a",
        "M1b",
        "M2a",
        "M3a",
        "M4a",
        "M0a",
        "M1a",
        "M2a",
        "M3b",
        "M4a",
        "M0c",
        "M1a",
        "M2a",
        "M3c",
        "M4b",
        "M0a",
        "M1b",
        "M2c",
        "M3a",
        "M4c",
        "M0a",
        "M1b",
        "M2a",
        "M3c",
        "M4c",
        "M0b",
        "M1b",
        "M2b",
        "M3a",
        "M4c",
        "M0a",
        "M1a",
        "M2a",
        "M3a",
        "M4a",
        "M0b",
        "M1b",
        "M2a",
        "M3a",
        "M4a",
        "M0a",
        "M1a",
        "M2a",
        "M3a",
        "M4a",
        "M0b",
        "M1a",
        "M2b",
        "M3c",
        "M4c",
        "M0b",
        "M1c",
        "M2a",
        "M3a",
        "M4a",
        "M0b",
        "M1c",
        "M2a",
        "M3b",
        "M4a",
        "M0c",
        "M1c",
        "M2a",
        "M3b",
        "M4b",
        "M0a",
        "M1b",
        "M2a",
        "M3b",
        "M4a",
        "M0a",
        "M1a",
        "M2c",
        "M3b",
        "M4c",
        "M0a",
        "M1a",
        "M2a",
        "M3a",
        "M4c",
        "M0a",
        "M1a",
        "M2a",
        "M3a",
        "M4a",
        "M0a",
        "M1b",
        "M2b",
        "M3c",
        "M4a",
        "M0a",
        "M1b",
        "M2a",
        "M3a",
        "M4b",
        "M0a",
        "M1a",
        "M2b",
        "M3b",
        "M4a",
        "M0c",
        "M1b",
        "M2a",
        "M3a",
        "M4c",
        "M0c",
        "M1b",
        "M2a",
        "M3b",
        "M4a",
        "M0a",
        "M1c",
        "M2a",
        "M3b",
        "M4a",
        "M0a",
        "M1c",
        "M2a",
        "M3b",
        "M4b",
        "M0a",
        "M1a",
        "M2a",
        "M3a",
        "M4a",
        "M0b",
        "M1b",
        "M2a",
        "M3a",
        "M4b",
        "M0b",
        "M1c",
        "M2c",
        "M3a",
        "M4a",
        "M0a",
        "M1b",
        "M2b",
        "M3b",
        "M4a",
        "M0a",
        "M1a",
        "M2c",
        "M3a",
        "M4a",
        "M0c",
        "M1a",
        "M2c",
        "M3a",
        "M4a",
        "M0a",
        "M1a",
        "M2a",
        "M3a",
        "M4a",
        "M0b",
        "M1c",
        "M2a",
        "M3c",
        "M4b",
        "M0c",
        "M1a",
        "M2c",
        "M3a",
        "M4b",
        "M0a",
        "M1a",
        "M2a",
        "M3b",
        "M4a"
      ]
    }
  ],
  "igd": 1.0556765040191798
}